zuffer/__init__.py
zuffer/cli.py
zuffer/commands/__init__.py
zuffer/commands/create_channels.py
zuffer/commands/embed.py
zuffer/commands/list.py
zuffer/commands/login.py
zuffer/commands/play_music.py
zuffer/commands/welcome.py
zuffer/core/__init__.py
zuffer/core/auth.py
zuffer/core/clients.py
zuffer/core/discord_api.py
zuffer/core/utils.py
zuffer/gui/embed_gui.py
zuffer/gui/welcomer_gui.py
zuffer-0.0.2.dist-info/METADATA
zuffer-0.0.2.dist-info/WHEEL
zuffer-0.0.2.dist-info/entry_points.txt
zuffer-0.0.2.dist-info/top_level.txt
zuffer-0.0.2.dist-info/RECORD
