Metadata-Version: 2.4
Name: zuffer
Version: 0.0.2
Summary: A cli utility to automate some tasks on your server
Author-email: Md Muzaffar <mdmuxaffar@gmail.com>
Classifier: Programming Language :: Python :: 3
Classifier: License :: OSI Approved :: MIT License
Classifier: Operating System :: OS Independent
Requires-Python: >=3.8
Requires-Dist: click>=8.0.0
Requires-Dist: discord.py>=2.0.0
Requires-Dist: questionary>=1.0.0
Requires-Dist: keyring>=23.0.0
Requires-Dist: pytest
Requires-Dist: Pillow>=11.1.0
Requires-Dist: requests>=2.20.0
Requires-Dist: aiohttp>=3.8.0
